fastTGA/__init__.py
fastTGA/main.py
fastTGA/models/__init__.py
fastTGA/models/google_spreadsheet_model.py
fastTGA/models/tga_dataset_model.py
fastTGA/models/tga_file.py
fastTGA/models/tga_tableview_model.py
fastTGA/models/txt_directory_model.py
fastTGA/services/__init__.py
fastTGA/services/data_filters.py
fastTGA/services/sample_repository.py
fastTGA/services/tga_entry_preparator.py
fastTGA/services/tga_import_service.py
fastTGA/ui/__init__.py
fastTGA/ui/converter.py
fastTGA/ui/data_overview_table_widget_ui.py
fastTGA/ui/data_widget_ui.py
fastTGA/ui/tga_data_preparation_widget_ui.py
fastTGA/viewmodels/__init__.py
fastTGA/viewmodels/data_widget_view_model.py
fastTGA/views/__init__.py
fastTGA/views/data_overview_table_widget.py
fastTGA/views/data_preparation_widget.py
fastTGA/views/data_widget.py
fastTGA/views/main_window.py
fastTGA-0.2.2.dist-info/METADATA
fastTGA-0.2.2.dist-info/WHEEL
fastTGA-0.2.2.dist-info/entry_points.txt
fastTGA-0.2.2.dist-info/top_level.txt
fastTGA-0.2.2.dist-info/RECORD
