Metadata-Version: 2.2
Name: fastTGA
Version: 0.2.2
Summary: A package for TGA data processing and management
Home-page: https://github.com/yourusername/fastTGA
Author: Manuel Leuchtenmüller
Author-email: manuel.leuchtenmueller@hydrogenreductionlab.com
Requires-Dist: PyQt6
Requires-Dist: gspread
Requires-Dist: polars
Dynamic: author
Dynamic: author-email
Dynamic: home-page
Dynamic: requires-dist
Dynamic: summary
